plm_cs/CS_predict.py
plm_cs/model.py
plm_cs-3.4.dist-info/LICENSE.txt
plm_cs-3.4.dist-info/METADATA
plm_cs-3.4.dist-info/WHEEL
plm_cs-3.4.dist-info/entry_points.txt
plm_cs-3.4.dist-info/top_level.txt
plm_cs-3.4.dist-info/zip-safe
plm_cs-3.4.dist-info/RECORD
